mimetype_match
