Metadata-Version: 1.1
Name: mimetype-match
Version: 1.0.3
Summary: A tool to make finding the appropriate mimetype to return easy
Home-page: https://github.com/timmartin19/mimetype-match
Author: Tim Martin
Author-email: tim.martin@vertical-knowledge.com
License: UNKNOWN
Keywords: H,T,T,P, ,p,y,t,h,o,n, ,A,c,c,e,p,t, ,H,e,a,d,e,r, ,H,T,T,P,_,A,C,C,E,P,T, ,m,i,m,e,t,y,p,e, ,m,a,t,c,h, ,C,o,n,t,e,n,t,-,T,y,p,e, ,c,o,n,t,e,n,t, ,t,y,p,e
Platform: UNKNOWN
Classifier: Development Status :: 3 - Alpha
Classifier: License :: OSI Approved :: GNU General Public License v2 (GPLv2)
Classifier: Programming Language :: Python
Classifier: Programming Language :: Python :: 2
Classifier: Programming Language :: Python :: 2.6
Classifier: Programming Language :: Python :: 2.7
Classifier: Programming Language :: Python :: 3
Classifier: Programming Language :: Python :: 3.3
Classifier: Programming Language :: Python :: 3.4
Classifier: Programming Language :: Python :: 3.5
Classifier: Programming Language :: Python :: Implementation :: PyPy
Classifier: Topic :: Software Development :: Libraries :: Python Modules
